cortex_sdk/__init__.py
cortex_sdk/configuration.py
cortex_sdk/api/__init__.py
cortex_sdk/api/api_resource.py
cortex_sdk/api/inferences.py
cortex_sdk/api/models.py
cortex_sdk/api/pipelines.py
cortex_sdk/api/repos.py
cortex_sdk/api/secrets.py
cortex_sdk/api/steps.py
cortex_sdk/api/users.py
cortex_sdk/types/__init__.py
cortex_sdk/types/cortex_base_type.py
cortex_sdk/types/cortex_file.py
cortex_sdk/types/cortex_inference.py
cortex_sdk/types/cortex_model.py
cortex_sdk/types/cortex_pipeline.py
cortex_sdk/types/cortex_repo.py
cortex_sdk/types/cortex_secret.py
cortex_sdk/types/cortex_step.py
cortex_sdk/types/cortex_user.py
cortex_sdk/util/__init__.py
cortex_sdk/util/file_provider.py
cortex_sdk-2.4.1.dist-info/METADATA
cortex_sdk-2.4.1.dist-info/WHEEL
cortex_sdk-2.4.1.dist-info/top_level.txt
cortex_sdk-2.4.1.dist-info/RECORD
