Metadata-Version: 2.1
Name: cortex-sdk
Version: 2.4.1
Summary: Nearly Human Cortex SDK dependency for interacting with APIs.
Author: Nearly Human
Author-email: support@nearlyhuman.ai
Keywords: nearlyhuman,nearly human,cortex,sdk
Requires-Python: >=3.8.10
Requires-Dist: requests >=2.31.0
Requires-Dist: setuptools
